mcmole3d/MCMole3D.py
mcmole3d/__init__.py
mcmole3d/mapping.py
mcmole3d/utils.py
mcmole3d_giuspugl-0.0.1.dist-info/LICENSE.txt
mcmole3d_giuspugl-0.0.1.dist-info/METADATA
mcmole3d_giuspugl-0.0.1.dist-info/WHEEL
mcmole3d_giuspugl-0.0.1.dist-info/top_level.txt
mcmole3d_giuspugl-0.0.1.dist-info/RECORD
