Metadata-Version: 2.1
Name: mcmole3d-giuspugl
Version: 0.0.1
Summary: Monte-Carlo realization of Galactic CO  emission
Home-page: https://github.com/giuspugl/MCMole3D
Author: Giuseppe Puglisi
Author-email: giuse.puglisi@gmail.com
License: UNKNOWN
Platform: UNKNOWN
Classifier: Programming Language :: Python :: 3
Classifier: License :: OSI Approved :: GNU Lesser General Public License v3 (LGPLv3)
Classifier: Operating System :: OS Independent
